Workbook

Sheet Leia-me
A1: PLANO DE ESTOQUE ESTRATÉGICO
A2: Análise de demanda, Safety Stock e Ponto de Reposição
A4: COMO ESTE MODELO FUNCIONA
A5: Fonte | B5: Gerado a partir de 'c85c99ad-Estoque_Claude.xlsx'.
A6: Base de data | B6: A demanda é datada pela 'DT Emissao' do pedido (sinal de demanda do cliente). Para usar a data de faturamento/entrega, altere V_DTEMISSAO no gerador.
A7: Janela de análise | B7: 2022-01 a 2026-06 (54 meses)
A8: Itens analisados | B8: 1478 (vendidos + componentes de estrutura)
A10: DEMANDA
A11: Demanda DIRETA | B11: Vendas do próprio item (aba Vendas, por mês).
A12: Demanda INDIRETA | B12: Consumo do item quando ele é componente de outro produto estruturado (BOM). Para cada estrutura pai->componente, o consumo segue as vendas do pai multiplicadas pela quantidade da estrutura.
A13: Demanda TOTAL | B13: Direta + Indireta, mês a mês.
A15: INDICADORES DE ESTOQUE
A16: Demanda média (μ) | B16: Média da demanda mensal total na janela.
A17: Desvio padrão (σ) | B17: Desvio padrão amostral da demanda mensal total.
A18: Lead Time (LT) | B18: Aba Cadastro, coluna 'Dias Entrega'. Convertido para meses dividindo por 30 dias/mês.
A19: Z-Score | B19: 1.645 (nível de serviço 95%).
A21: FÓRMULAS
A22: Safety Stock | B22: SS = Z × σ × √(Lead Time em meses)
A23: Ponto de Reposição | B23: ROP = (μ × Lead Time em meses) + Safety Stock
A24: Demanda no Lead Time | B24: μ × Lead Time (em meses)
A26: PARÂMETROS AJUSTÁVEIS | B26: Veja a aba 'Parâmetros'. Ao alterar o Z-Score, as colunas de Safety Stock e Ponto de Reposição recalculam automaticamente.
A28: ABAS
A29: Parâmetros | B29: Nível de serviço / Z-Score / dias por mês.
A30: Análise de Demanda | B30: Ranking, demanda direta/indireta/total, médias.
A31: Indicadores de Estoque | B31: Safety Stock e Ponto de Reposição por item.
A32: Demanda Mensal (D+I) | B32: Matriz item × mês da demanda total.
A33: Demanda Semestral | B33: Demanda total consolidada por semestre.
A34: Ranking Top 50 | B34: Itens mais demandados (com gráfico).
A35: Uso em Estruturas (BOM) | B35: Estruturas em que cada item é componente.
A36: Base Vendas / Cadastro / BOM | B36: Dados de origem para auditoria.

Sheet Parâmetros
A1: PARÂMETROS
A2: Edite as células amarelas — o modelo recalcula.
A4: Parâmetro | B4: Valor
A5: Nível de serviço | B5: 0.95
A6: Z-Score | B6: 1.645
A7: Dias por mês | B7: 30
A9: Dica: nível de serviço 90%→Z=1.282, 95%→1.645, 97.5%→1.960, 99%→2.326.

Sheet Análise de Demanda
A1: ANÁLISE DE DEMANDA
A2: Demanda direta, indireta e total por item — janela 2022-01 a 2026-06
A4: Rank | B4: Código | C4: Descrição | D4: Tipo | E4: Un | F4: Lead Time (dias) | G4: Demanda Direta (un) | H4: Demanda Indireta (un) | I4: Demanda Total (un) | J4: % do Total | K4: Média Mensal | L4: Média Semestral | M4: Desvio Padrão Mensal
A5: 1 | B5: A212001.013 | C5: TERMINAL CRIMPAVEL PARA CONECTOR MODULAR - 4A - RETO - BITOLA 0,25 - 0,75MM² | D5: PA | E5: PC | F5: 75 | G5: 5605 | H5: 0 | I5: 5605 | J5: 0.1490521 | K5: 103.796 | L5: 622.778 | M5: 160.555
A6: 2 | B6: A100106.013 | C6: CABO EXTRA FLEXIVEL 6 PARES TRANCADOS 0,25MM2 PARA ENCODERS | D6: PA | E6: M | F6: 25 | G6: 3655 | H6: 0 | I6: 3655 | J6: 0.097196331 | K6: 67.685 | L6: 406.111 | M6: 167.796
A7: 3 | B7: A100106.012 | C7: CABO EXTRA FLEXIVEL 6 PARES TRANCADOS PARA ENCODERS | D7: PA | E7: M | F7: 44 | G7: 2624 | H7: 0 | I7: 2624 | J7: 0.069779254 | K7: 48.593 | L7: 291.556 | M7: 313.613
A8: 4 | B8: AG00105.105 | C8: CABO UTP BLINDADO GIGALAN CAT.6 VERMELHO | D8: MP | E8: PC | F8: 25 | G8: 1985 | H8: 0 | I8: 1985 | J8: 0.052786516 | K8: 36.759 | L8: 220.556 | M8: 101.606
A9: 5 | B9: C430-00001 | C9: CONECTOR ROTATIVO MODULAR 430, 2X4A E 2X30A | D9: PA | E9: PC | F9: 75 | G9: 1863 | H9: 0 | I9: 1863 | J9: 0.049542207 | K9: 34.5 | L9: 207 | M9: 20.091
A10: 6 | B10: A100106.105 | C10: CABO FLEXIVEL 4 PARES 0,5MM² PARA SINAL ANALOGICO | D10: PA | E10: M | F10: 25 | G10: 1750 | H10: 0 | I10: 1750 | J10: 0.046537231 | K10: 32.407 | L10: 194.444 | M10: 170.227
A11: 7 | B11: A212001.012 | C11: TERMINAL CRIMPAVEL PARA CONECTOR MODULAR - 30A - RETO - BITOLA 1,5 - 2MM² | D11: PA | E11: PC | F11: 75 | G11: 1202 | H11: 0 | I11: 1202 | J11: 0.03196443 | K11: 22.259 | L11: 133.556 | M11: 49.281
A12: 8 | B12: ADS01423.003 | C12: TELA PARA WINDFENCE DUSTTAMER 6510 VERDE PERM 50 L 150CM (59 | D12: PA | E12: M | F12: 60 | G12: 1080 | H12: 0 | I12: 1080 | J12: 0.02872012 | K12: 20 | L12: 120 | M12: 102.938
A13: 9 | B13: A212001.015 | C13: TERMINAL CRIMPAVEL PARA CONECTOR MODULAR - 30A - 90º - BITOLA 1,5 - 2MM² | D13: PA | E13: PC | F13: 75 | G13: 821 | H13: 0 | I13: 821 | J13: 0.02183261 | K13: 15.204 | L13: 91.222 | M13: 43.938
A14: 10 | B14: C205-00001 | C14: CONECTOR ROTATIVO COAXIAL 205, 2X4A | D14: PA | E14: PC | F14: 75 | G14: 784 | H14: 0 | I14: 784 | J14: 0.02084868 | K14: 14.519 | L14: 87.111 | M14: 10.495
A15: 11 | B15: A212001.011 | C15: ESPAQUETE TERMOENCOLHIVEL PARA ISOLACAO DE TERMINAIS CRIMPAVEIS | D15: PA | E15: PC | F15: 75 | G15: 783 | H15: 0 | I15: 783 | J15: 0.020822087 | K15: 14.5 | L15: 87 | M15: 59.938
A16: 12 | B16: STR04196.001 | C16: SERVICO DE ASSESSORIA DE VENDAS ID | D16: SV | E16: HR | F16: 90 | G16: 608 | H16: 0 | I16: 608 | J16: 0.016168364 | K16: 11.259 | L16: 67.556 | M16: 18.452
... A1482: 1478 | B1482: NNS0-00267 | C1482: MANETE GAA1441H1ESPESP 2X OER8B 1N G251BK2BK3GN4RD5WH6BK | D1482: PA | E1482: PC | F1482: 115 | G1482: 1 | H1482: 0 | I1482: 1 | J1482: 2.6592703e-05 | K1482: 0.019 | L1482: 0.111 | M1482: 0.136

Sheet Indicadores de Estoque
A1: INDICADORES DE ESTOQUE
A2: Safety Stock = Z×σ×√LT | Ponto de Reposição = (μ×LT) + SS
A4: Código | B4: Descrição | C4: Tipo | D4: Lead Time (dias) | E4: Lead Time (meses) | F4: Demanda Média Mensal (μ) | G4: Desvio Padrão Mensal (σ) | H4: CV (σ/μ) | I4: Z-Score | J4: Demanda no Lead Time | K4: Safety Stock (un) | L4: Ponto de Reposição (un)
A5: A212001.013 | B5: TERMINAL CRIMPAVEL PARA CONECTOR MODULAR - 4A - RETO - BITOLA 0,25 - 0,75MM² | C5: PA | D5: 75 | E5: =IF(D5="","",D5/Parâmetros!$B$7) | F5: 103.7963 | G5: 160.55498 | H5: =IF(F5=0,"",G5/F5) | I5: =Parâmetros!$B$6 | J5: =IF(E5="","",F5*E5) | K5: =IF(E5="","",I5*G5*SQRT(E5)) | L5: =IF(E5="","",J5+K5)
A6: A100106.013 | B6: CABO EXTRA FLEXIVEL 6 PARES TRANCADOS 0,25MM2 PARA ENCODERS | C6: PA | D6: 25 | E6: =IF(D6="","",D6/Parâmetros!$B$7) | F6: 67.685185 | G6: 167.79568 | H6: =IF(F6=0,"",G6/F6) | I6: =Parâmetros!$B$6 | J6: =IF(E6="","",F6*E6) | K6: =IF(E6="","",I6*G6*SQRT(E6)) | L6: =IF(E6="","",J6+K6)
A7: A100106.012 | B7: CABO EXTRA FLEXIVEL 6 PARES TRANCADOS PARA ENCODERS | C7: PA | D7: 44 | E7: =IF(D7="","",D7/Parâmetros!$B$7) | F7: 48.592593 | G7: 313.61258 | H7: =IF(F7=0,"",G7/F7) | I7: =Parâmetros!$B$6 | J7: =IF(E7="","",F7*E7) | K7: =IF(E7="","",I7*G7*SQRT(E7)) | L7: =IF(E7="","",J7+K7)
A8: AG00105.105 | B8: CABO UTP BLINDADO GIGALAN CAT.6 VERMELHO | C8: MP | D8: 25 | E8: =IF(D8="","",D8/Parâmetros!$B$7) | F8: 36.759259 | G8: 101.60577 | H8: =IF(F8=0,"",G8/F8) | I8: =Parâmetros!$B$6 | J8: =IF(E8="","",F8*E8) | K8: =IF(E8="","",I8*G8*SQRT(E8)) | L8: =IF(E8="","",J8+K8)
A9: C430-00001 | B9: CONECTOR ROTATIVO MODULAR 430, 2X4A E 2X30A | C9: PA | D9: 75 | E9: =IF(D9="","",D9/Parâmetros!$B$7) | F9: 34.5 | G9: 20.091066 | H9: =IF(F9=0,"",G9/F9) | I9: =Parâmetros!$B$6 | J9: =IF(E9="","",F9*E9) | K9: =IF(E9="","",I9*G9*SQRT(E9)) | L9: =IF(E9="","",J9+K9)
A10: A100106.105 | B10: CABO FLEXIVEL 4 PARES 0,5MM² PARA SINAL ANALOGICO | C10: PA | D10: 25 | E10: =IF(D10="","",D10/Parâmetros!$B$7) | F10: 32.407407 | G10: 170.22665 | H10: =IF(F10=0,"",G10/F10) | I10: =Parâmetros!$B$6 | J10: =IF(E10="","",F10*E10) | K10: =IF(E10="","",I10*G10*SQRT(E10)) | L10: =IF(E10="","",J10+K10)
A11: A212001.012 | B11: TERMINAL CRIMPAVEL PARA CONECTOR MODULAR - 30A - RETO - BITOLA 1,5 - 2MM² | C11: PA | D11: 75 | E11: =IF(D11="","",D11/Parâmetros!$B$7) | F11: 22.259259 | G11: 49.280937 | H11: =IF(F11=0,"",G11/F11) | I11: =Parâmetros!$B$6 | J11: =IF(E11="","",F11*E11) | K11: =IF(E11="","",I11*G11*SQRT(E11)) | L11: =IF(E11="","",J11+K11)
A12: ADS01423.003 | B12: TELA PARA WINDFENCE DUSTTAMER 6510 VERDE PERM 50 L 150CM (59 | C12: PA | D12: 60 | E12: =IF(D12="","",D12/Parâmetros!$B$7) | F12: 20 | G12: 102.93797 | H12: =IF(F12=0,"",G12/F12) | I12: =Parâmetros!$B$6 | J12: =IF(E12="","",F12*E12) | K12: =IF(E12="","",I12*G12*SQRT(E12)) | L12: =IF(E12="","",J12+K12)
A13: A212001.015 | B13: TERMINAL CRIMPAVEL PARA CONECTOR MODULAR - 30A - 90º - BITOLA 1,5 - 2MM² | C13: PA | D13: 75 | E13: =IF(D13="","",D13/Parâmetros!$B$7) | F13: 15.203704 | G13: 43.937511 | H13: =IF(F13=0,"",G13/F13) | I13: =Parâmetros!$B$6 | J13: =IF(E13="","",F13*E13) | K13: =IF(E13="","",I13*G13*SQRT(E13)) | L13: =IF(E13="","",J13+K13)
A14: C205-00001 | B14: CONECTOR ROTATIVO COAXIAL 205, 2X4A | C14: PA | D14: 75 | E14: =IF(D14="","",D14/Parâmetros!$B$7) | F14: 14.518519 | G14: 10.494816 | H14: =IF(F14=0,"",G14/F14) | I14: =Parâmetros!$B$6 | J14: =IF(E14="","",F14*E14) | K14: =IF(E14="","",I14*G14*SQRT(E14)) | L14: =IF(E14="","",J14+K14)
A15: A212001.011 | B15: ESPAQUETE TERMOENCOLHIVEL PARA ISOLACAO DE TERMINAIS CRIMPAVEIS | C15: PA | D15: 75 | E15: =IF(D15="","",D15/Parâmetros!$B$7) | F15: 14.5 | G15: 59.93794 | H15: =IF(F15=0,"",G15/F15) | I15: =Parâmetros!$B$6 | J15: =IF(E15="","",F15*E15) | K15: =IF(E15="","",I15*G15*SQRT(E15)) | L15: =IF(E15="","",J15+K15)
A16: STR04196.001 | B16: SERVICO DE ASSESSORIA DE VENDAS ID | C16: SV | D16: 90 | E16: =IF(D16="","",D16/Parâmetros!$B$7) | F16: 11.259259 | G16: 18.451553 | H16: =IF(F16=0,"",G16/F16) | I16: =Parâmetros!$B$6 | J16: =IF(E16="","",F16*E16) | K16: =IF(E16="","",I16*G16*SQRT(E16)) | L16: =IF(E16="","",J16+K16)
... A1482: NNS0-00267 | B1482: MANETE GAA1441H1ESPESP 2X OER8B 1N G251BK2BK3GN4RD5WH6BK | C1482: PA | D1482: 115 | E1482: =IF(D1482="","",D1482/Parâmetros!$B$7) | F1482: 0.018519 | G1482: 0.136083 | H1482: =IF(F1482=0,"",G1482/F1482) | I1482: =Parâmetros!$B$6 | J1482: =IF(E1482="","",F1482*E1482) | K1482: =IF(E1482="","",I1482*G1482*SQRT(E1482)) | L1482: =IF(E1482="","",J1482+K1482)

Sheet Demanda Mensal (D+I)
A1: DEMANDA MENSAL (DIRETA + INDIRETA)
A2: Matriz item × mês da demanda total
A4: Código | B4: Descrição | C4: 2022-01 | D4: 2022-02 | E4: 2022-03 | F4: 2022-04 | G4: 2022-05 | H4: 2022-06 | I4: 2022-07 | J4: 2022-08 | K4: 2022-09 | L4: 2022-10 | M4: 2022-11 | N4: 2022-12 | O4: 2023-01 | P4: 2023-02 | Q4: 2023-03 | R4: 2023-04 | S4: 2023-05 | T4: 2023-06 | U4: 2023-07 | V4: 2023-08 | W4: 2023-09 | X4: 2023-10 | Y4: 2023-11 | Z4: 2023-12 | AA4: 2024-01 | AB4: 2024-02 | AC4: 2024-03 | AD4: 2024-04 | AE4: 2024-05 | AF4: 2024-06 | AG4: 2024-07 | AH4: 2024-08 | AI4: 2024-09 | AJ4: 2024-10 | AK4: 2024-11 | AL4: 2024-12 | AM4: 2025-01 | AN4: 2025-02 | AO4: 2025-03 | AP4: 2025-04 | AQ4: 2025-05 | AR4: 2025-06 | AS4: 2025-07 | AT4: 2025-08 | AU4: 2025-09 | AV4: 2025-10 | AW4: 2025-11 | AX4: 2025-12 | AY4: 2026-01 | AZ4: 2026-02 | BA4: 2026-03 | BB4: 2026-04 | BC4: 2026-05 | BD4: 2026-06 | BE4: Total
A5: A212001.013 | B5: TERMINAL CRIMPAVEL PARA CONECTOR MODULAR - 4A - RETO - BITOLA 0,25 - 0,75MM² | E5: 133 | H5: 30 | I5: 40 | K5: 20 | L5: 520 | M5: 10 | O5: 8 | P5: 336 | R5: 150 | T5: 1 | U5: 133 | W5: 240 | X5: 406 | Y5: 500 | AA5: 200 | AB5: 150 | AC5: 16 | AD5: 500 | AE5: 2 | AF5: 4 | AG5: 400 | AH5: 180 | AJ5: 20 | AN5: 16 | AO5: 100 | AP5: 100 | AQ5: 100 | AS5: 530 | AT5: 100 | AV5: 100 | AY5: 40 | BB5: 90 | BC5: 430 | BE5: 5605
A6: A100106.013 | B6: CABO EXTRA FLEXIVEL 6 PARES TRANCADOS 0,25MM2 PARA ENCODERS | C6: 430 | D6: 100 | E6: 400 | H6: 250 | J6: 900 | K6: 250 | L6: 10 | N6: 135 | Q6: 50 | Z6: 100 | AM6: 50 | AO6: 500 | AP6: 80 | AQ6: 400 | BE6: 3655
A7: A100106.012 | B7: CABO EXTRA FLEXIVEL 6 PARES TRANCADOS PARA ENCODERS | M7: 200 | Y7: 100 | AE7: 2 | AG7: 2 | AL7: 10 | AR7: 10 | AU7: 2300 | BE7: 2624
A8: AG00105.105 | B8: CABO UTP BLINDADO GIGALAN CAT.6 VERMELHO | O8: 50 | P8: 550 | S8: 150 | T8: 115 | V8: 20 | Z8: 180 | AE8: 50 | AJ8: 270 | AK8: 200 | AR8: 40 | AS8: 360 | BE8: 1985
A9: C430-00001 | B9: CONECTOR ROTATIVO MODULAR 430, 2X4A E 2X30A | D9: 1 | E9: 22 | F9: 22 | G9: 28 | H9: 35 | I9: 18 | J9: 28 | K9: 51 | L9: 27 | M9: 13 | N9: 10 | O9: 37 | P9: 44 | Q9: 31 | R9: 28 | S9: 29 | T9: 47 | U9: 10 | V9: 36 | W9: 41 | X9: 53 | Y9: 68 | Z9: 27 | AA9: 32 | AB9: 25 | AC9: 28 | AD9: 48 | AE9: 56 | AF9: 51 | AG9: 56 | AH9: 63 | AI9: 15 | AJ9: 36 | AK9: 14 | AL9: 39 | AM9: 31 | AN9: 58 | AO9: 57 | AP9: 16 | AQ9: 72 | AR9: 67 | AS9: 51 | AT9: 43 | AU9: 43 | AV9: 90 | AW9: 41 | AX9: 51 | AY9: 34 | AZ9: 11 | BA9: 10 | BB9: 3 | BC9: 16 | BE9: 1863
A10: A100106.105 | B10: CABO FLEXIVEL 4 PARES 0,5MM² PARA SINAL ANALOGICO | J10: 1050 | AK10: 700 | BE10: 1750
A11: A212001.012 | B11: TERMINAL CRIMPAVEL PARA CONECTOR MODULAR - 30A - RETO - BITOLA 1,5 - 2MM² | E11: 125 | H11: 27 | K11: 20 | P11: 50 | R11: 161 | W11: 50 | X11: 100 | Y11: 200 | AA11: 50 | AB11: 8 | AD11: 200 | AE11: 23 | AL11: 112 | AO11: 12 | AS11: 20 | AT11: 4 | BB11: 40 | BE11: 1202
A12: ADS01423.003 | B12: TELA PARA WINDFENCE DUSTTAMER 6510 VERDE PERM 50 L 150CM (59 | Y12: 540 | Z12: 540 | BE12: 1080
A13: A212001.015 | B13: TERMINAL CRIMPAVEL PARA CONECTOR MODULAR - 30A - 90º - BITOLA 1,5 - 2MM² | E13: 16 | H13: 27 | I13: 50 | O13: 4 | T13: 2 | Y13: 200 | AA13: 164 | AC13: 21 | AD13: 200 | AF13: 8 | AI13: 39 | AJ13: 20 | AN13: 16 | AQ13: 40 | AR13: 10 | AT13: 4 | BE13: 821
A14: C205-00001 | B14: CONECTOR ROTATIVO COAXIAL 205, 2X4A | D14: 3 | E14: 10 | F14: 4 | G14: 11 | H14: 32 | I14: 8 | J14: 12 | K14: 4 | L14: 8 | M14: 27 | N14: 4 | O14: 3 | P14: 2 | Q14: 6 | R14: 16 | S14: 11 | T14: 16 | U14: 21 | V14: 7 | W14: 41 | X14: 24 | Y14: 10 | Z14: 15 | AA14: 29 | AB14: 26 | AC14: 18 | AD14: 12 | AE14: 23 | AF14: 32 | AG14: 15 | AH14: 35 | AI14: 10 | AJ14: 4 | AK14: 15 | AL14: 5 | AM14: 32 | AN14: 13 | AO14: 18 | AP14: 20 | AQ14: 19 | AR14: 10 | AS14: 19 | AT14: 12 | AU14: 2 | AV14: 35 | AW14: 1 | AX14: 8 | AY14: 7 | AZ14: 33 | BA14: 17 | BB14: 6 | BC14: 13 | BE14: 784
A15: A212001.011 | B15: ESPAQUETE TERMOENCOLHIVEL PARA ISOLACAO DE TERMINAIS CRIMPAVEIS | E15: 125 | H15: 20 | L15: 400 | Q15: 10 | R15: 150 | AM15: 3 | AS15: 25 | BB15: 50 | BE15: 783
A16: STR04196.001 | B16: SERVICO DE ASSESSORIA DE VENDAS ID | C16: 1 | D16: 2 | E16: 22 | F16: 25 | G16: 28 | I16: 1 | J16: 2 | K16: 16 | L16: 34 | N16: 94 | O16: 3 | P16: 1 | Q16: 58 | S16: 3 | T16: 33 | U16: 6 | V16: 13 | W16: 34 | Y16: 42 | AA16: 19 | AB16: 3 | AC16: 1 | AD16: 1 | AE16: 1 | AF16: 10 | AG16: 5 | AH16: 3 | AI16: 2 | AJ16: 7 | AL16: 28 | AM16: 1 | AO16: 8 | AP16: 58 | AQ16: 8 | AT16: 15 | AV16: 5 | AW16: 1 | AX16: 1 | AY16: 6 | BA16: 2 | BB16: 2 | BC16: 3 | BE16: 608
A17: C430-00002 | B17: CONECTOR ROTATIVO MODULAR 430-SS, 4X30A | E17: 4 | F17: 6 | G17: 11 | I17: 10 | J17: 4 | K17: 4 | L17: 6 | N17: 8 | O17: 15 | P17: 5 | Q17: 11 | R17: 7 | S17: 4 | T17: 4 | U17: 3 | V17: 6 | W17: 2 | X17: 25 | Y17: 3 | AA17: 4 | AB17: 8 | AC17: 7 | AD17: 10 | AE17: 4 | AF17: 16 | AG17: 17 | AH17: 7 | AI17: 14 | AJ17: 15 | AM17: 22 | AN17: 28 | AP17: 4 | AQ17: 22 | AR17: 16 | AS17: 2 | AT17: 18 | AU17: 7 | AV17: 9 | AX17: 16 | AY17: 7 | AZ17: 27 | BA17: 20 | BB17: 59 | BC17: 42 | BE17: 539
A18: AG01137.002 | B18: SONDA DE AMOSTRAGEM TLC-40-150-ZR1 | AK18: 224 | BA18: 280 | BE18: 504
A19: ADS01127.003 | B19: CORDOALHA PARA AMARRAÇÃO DA TELA PARA WINDFENCE | Y19: 450 | BE19: 450
A20: A212001.005 | B20: SOQUETE DE 2 POLOS PARA CONECTOR COAXIAL 205 COM 2 TERMINAIS SOLDAVEIS | E20: 7 | G20: 8 | H20: 19 | I20: 8 | J20: 7 | K20: 15 | L20: 4 | M20: 3 | N20: 6 | O20: 8 | Q20: 8 | R20: 5 | S20: 6 | T20: 1 | V20: 5 | W20: 10 | X20: 25 | Y20: 5 | Z20: 5 | AA20: 5 | AB20: 19 | AC20: 7 | AD20: 1 | AE20: 15 | AF20: 26 | AG20: 13 | AH20: 12 | AI20: 4 | AJ20: 8 | AK20: 7 | AL20: 7 | AM20: 7 | AN20: 10 | AO20: 14 | AP20: 5 | AQ20: 13 | AR20: 4 | AS20: 16 | AT20: 11 | AU20: 1 | AV20: 16 | AW20: 7 | AX20: 2 | AY20: 1 | AZ20: 18 | BA20: 5 | BB20: 12 | BC20: 4 | BE20: 425
A21: A100106.113 | B21: CABO PROFINET TIPO B 2 PARES 22 AWG | AW21: 420 | BE21: 420
A22: A212003.003 | B22: KIT PLUGS COMPLETO MONTADO PARA CONECTOR 430 C/ 4 RABICHOS DE 30 CM | E22: 5 | F22: 8 | J22: 6 | M22: 12 | N22: 2 | P22: 8 | Q22: 14 | S22: 4 | T22: 4 | U22: 12 | V22: 4 | X22: 6 | Y22: 4 | Z22: 40 | AA22: 4 | AC22: 1 | AD22: 5 | AE22: 14 | AF22: 44 | AG22: 5 | AI22: 19 | AM22: 2 | AN22: 29 | AP22: 12 | AQ22: 8 | AT22: 35 | AV22: 27 | AY22: 8 | AZ22: 4 | BA22: 20 | BB22: 12 | BC22: 11 | BE22: 389
A23: AG00107.059 | B23: PASSA CABO EM BORRACHA P/ VNSK | C23: 8 | D23: 6 | E23: 2 | F23: 6 | G23: 3 | H23: 4 | I23: 5 | J23: 3 | K23: 4 | L23: 9 | M23: 5 | N23: 7 | O23: 14 | P23: 6 | Q23: 5 | R23: 7 | S23: 8 | T23: 3 | U23: 11 | V23: 8 | W23: 12 | X23: 5 | Y23: 3 | Z23: 4 | AA23: 19 | AB23: 14 | AC23: 10 | AD23: 10 | AE23: 22 | AF23: 14 | AG23: 12 | AH23: 7 | AI23: 9 | AJ23: 19 | AK23: 9 | AM23: 4 | AO23: 6 | AP23: 3 | AQ23: 1 | AR23: 5 | AS23: 13 | AT23: 7 | AU23: 8 | AV23: 4 | AW23: 2 | AX23: 4 | AY23: 2 | AZ23: 7 | BA23: 4 | BB23: 9 | BC23: 8 | BE23: 380
A24: AG01122.009 | B24: SONDA DE AMOSTRAGEM POR IMERSÃO TLC-25-120-ZR1 | AG24: 20 | AS24: 35 | BB24: 280 | BE24: 335
A25: AG01122.007 | B25: SONDA DE AMOSTRAGEM POR IMERSÃO TB-25-120-ZR1 | AG25: 20 | AS25: 10 | BB25: 280 | BE25: 310
A26: A100106.053 | B26: CABO BLINDADO 3 PARES TRANÇADOS 0,5MM² PARA ENCODERS | AH26: 3 | AM26: 260 | AN26: 10 | AR26: 20 | AU26: 10 | BE26: 303
A27: A301205.067 | B27: COIFA PARA ESPELHO DE 96X96MM V041N | E27: 2 | F27: 6 | G27: 2 | H27: 5 | I27: 2 | J27: 5 | K27: 1 | L27: 9 | N27: 6 | O27: 4 | P27: 39 | Q27: 10 | R27: 5 | S27: 2 | U27: 3 | V27: 1 | W27: 1 | Y27: 6 | AA27: 9 | AB27: 4 | AC27: 23 | AD27: 1 | AE27: 2 | AF27: 4 | AG27: 2 | AI27: 2 | AK27: 15 | AM27: 8 | AN27: 12 | AO27: 6 | AS27: 8 | AT27: 4 | AU27: 10 | AV27: 12 | AW27: 6 | AY27: 8 | BA27: 6 | BB27: 4 | BE27: 255
A28: A212001.007 | B28: RECEPTACULO DE 2 POLOS PARA CONECTOR COAXIAL 205 COM 2 RABICHOS DE 15CM | E28: 1 | F28: 7 | G28: 8 | H28: 5 | I28: 3 | J28: 5 | K28: 11 | M28: 2 | O28: 7 | Q28: 6 | R28: 5 | T28: 10 | W28: 16 | Y28: 5 | Z28: 1 | AA28: 2 | AD28: 6 | AE28: 4 | AF28: 11 | AH28: 6 | AI28: 1 | AJ28: 5 | AK28: 17 | AM28: 11 | AO28: 11 | AP28: 3 | AT28: 7 | AU28: 3 | AV28: 16 | AW28: 3 | AX28: 2 | AY28: 1 | AZ28: 8 | BA28: 5 | BB28: 22 | BC28: 5 | BE28: 241
A29: A100106.001 | B29: CABO COM MALHA TRANCADA 26X0,14MM2 | U29: 100 | Y29: 15 | AI29: 100 | BE29: 215
A30: A212001.006 | B30: RECEPTÁCULO DE 2 POLOS PARA CONECTOR COAXIAL 205 COM TERMINAL SOLDÁVEL | E30: 4 | H30: 19 | K30: 2 | M30: 3 | R30: 3 | W30: 10 | X30: 25 | Y30: 18 | Z30: 3 | AB30: 14 | AC30: 9 | AE30: 12 | AF30: 14 | AG30: 10 | AH30: 2 | AI30: 2 | AN30: 12 | AO30: 1 | AP30: 5 | AQ30: 8 | AT30: 6 | AU30: 1 | AV30: 9 | AW30: 4 | AX30: 2 | AZ30: 1 | BA30: 6 | BC30: 1 | BE30: 206
A31: A300200.017 | B31: MODULO DE CONTATO P/ NS0 | H31: 10 | O31: 20 | R31: 10 | S31: 3 | T31: 1 | U31: 20 | Y31: 5 | Z31: 8 | AA31: 2 | AC31: 2 | AG31: 41 | AJ31: 6 | AL31: 10 | AO31: 4 | AR31: 6 | AS31: 20 | AU31: 6 | AV31: 6 | AY31: 12 | BC31: 4 | BE31: 196
A32: A301205.434 | B32: COIFA PARA MANETE VNS0 NNS0 VCS0 HS2 27 | D32: 5 | F32: 10 | K32: 4 | O32: 12 | Q32: 13 | R32: 10 | S32: 10 | T32: 4 | AB32: 2 | AD32: 2 | AF32: 3 | AH32: 10 | AJ32: 5 | AM32: 1 | AN32: 26 | AP32: 15 | AR32: 4 | AS32: 5 | AT32: 22 | AY32: 5 | AZ32: 15 | BB32: 4 | BC32: 8 | BE32: 195
A33: A100106.004 | B33: CABO BLINDADO FLEXIVEL PARA ENCODER SSI | S33: 100 | AQ33: 80 | BE33: 180
A34: A300200.054 | B34: BOTAO 1NA P9F | D34: 14 | O34: 12 | Q34: 5 | S34: 10 | T34: 30 | U34: 21 | Y34: 5 | Z34: 12 | AG34: 11 | AH34: 15 | AM34: 7 | AO34: 10 | AT34: 3 | AU34: 6.1 | BB34: 14 | BE34: 175.1
A35: A101409.086 | B35: BRACO DE TORQUE COMP. 100MM 6MM | AI35: 40 | AK35: 120 | BE35: 160
A36: A100106.023 | B36: CABO BLINDADO FLEXIVEL 4X0,25MM PAR TRANCADO | AE36: 150 | BE36: 150
A37: C630-00001 | B37: CONECTOR ROTATIVO MODULAR 630, 2X4A E 4X30A | E37: 2 | G37: 2 | H37: 7 | I37: 2 | K37: 1 | N37: 2 | O37: 4 | R37: 3 | S37: 1 | T37: 13 | U37: 5 | V37: 3 | W37: 1 | X37: 1 | Y37: 1 | Z37: 1 | AA37: 1 | AB37: 4 | AC37: 6 | AD37: 2 | AE37: 3 | AF37: 6 | AG37: 7 | AH37: 3 | AI37: 2 | AJ37: 2 | AK37: 1 | AL37: 1 | AM37: 1 | AN37: 1 | AO37: 2 | AQ37: 4 | AR37: 2 | AS37: 3 | AT37: 4 | AU37: 5 | AV37: 3 | AW37: 3 | AX37: 7 | AY37: 2 | AZ37: 3 | BA37: 3 | BB37: 1 | BC37: 6 | BE37: 137
A38: A111009.007 | B38: CONECTOR 4 POLOS M12 FEMEA ACODED | F38: 3 | G38: 2 | I38: 2 | J38: 1 | K38: 15 | O38: 10 | P38: 4 | Q38: 34 | R38: 5 | S38: 14 | T38: 5 | V38: 4 | Y38: 4 | AA38: 24 | AD38: 3 | AL38: 2 | AN38: 2 | AP38: 1 | BE38: 135
A39: AOR00106.127 | B39: MULTICABO 12 VIAS (1 COAXIAL, 12 DADOS) | AP39: 125 | BE39: 125
A40: C230-00001 | B40: CONECTOR ROTATIVO MODULAR 230, 2X30A | E40: 1 | F40: 4 | G40: 2 | H40: 7 | K40: 1 | L40: 5 | M40: 1 | P40: 1 | Q40: 1 | R40: 2 | T40: 2 | V40: 7 | W40: 3 | X40: 1 | Y40: 1 | Z40: 1 | AA40: 3 | AB40: 6 | AC40: 8 | AD40: 1 | AH40: 10 | AK40: 6 | AM40: 1 | AN40: 9 | AO40: 4 | AT40: 7 | AU40: 3 | AX40: 1 | AY40: 3 | BA40: 6 | BC40: 10 | BE40: 118
A41: AG00102.388 | B41: REGUA DE BORNES PARA SISTEMA FRISOLUB SEM DISJUNTOR | L41: 108 | AD41: 1 | BE41: 109
A42: C230-00002 | B42: CONECTOR ROTATIVO MODULAR 230-SS, 2X30A | F42: 5 | H42: 5 | I42: 2 | J42: 2 | O42: 2 | S42: 6 | U42: 3 | V42: 3 | W42: 3 | AB42: 7 | AC42: 4 | AE42: 2 | AF42: 1 | AI42: 2 | AJ42: 3 | AK42: 4 | AM42: 8 | AN42: 2 | AP42: 4 | AR42: 3 | AS42: 6 | AT42: 2 | AU42: 6 | AV42: 4 | AW42: 1 | AX42: 6 | AZ42: 2 | BC42: 2 | BE42: 100
A43: A212001.017 | B43: TERMINAL CRIMPAVEL PARA CONECTOR MODULAR - 30A - RETO- C/ PROTECAO - BITOLA 3-6MM2 | E43: 25 | Q43: 10 | AM43: 3 | AS43: 20 | BB43: 40 | BE43: 98
A44: T65VAVMDP-0001 | B44: ENCODER ABSOLUTO CEV-65-M-DP 4096/4096 | D44: 2 | E44: 2 | F44: 8 | I44: 2 | J44: 5 | K44: 3 | L44: 1 | P44: 2 | R44: 8 | X44: 3 | AB44: 5 | AE44: 10 | AG44: 2 | AH44: 2 | AI44: 4 | AJ44: 3 | AK44: 2 | AL44: 3 | AO44: 5 | AP44: 2 | AQ44: 1 | AR44: 6 | AS44: 5 | AT44: 4 | AV44: 1 | AY44: 1 | AZ44: 1 | BB44: 2 | BE44: 95
A45: A212001.014 | B45: TERMINAL CRIMPAVEL PARA CONECTOR MODULAR - 30A - RETO - BITOLA 1,5 - 2MM2 | E45: 25 | M45: 10 | AS45: 20 | BB45: 40 | BE45: 95
A46: A301205.435 | B46: COIFA PARA MANETE VNS0 E VCS0 HS2 27 UGA | O46: 11 | P46: 2 | U46: 10 | Y46: 5 | Z46: 8 | AA46: 2 | AB46: 8 | AG46: 21 | AL46: 2 | AM46: 2 | AN46: 6 | AO46: 3 | AR46: 4 | AS46: 1 | AT46: 1 | AU46: 0.1 | AZ46: 2 | BB46: 3 | BE46: 91.1
A47: A111009.006 | B47: CONECTOR 4 POLOS M12 MACHO DCODED | G47: 4 | J47: 1 | K47: 14 | O47: 10 | P47: 4 | Q47: 4 | R47: 5 | S47: 14 | V47: 4 | Y47: 4 | AA47: 24 | AL47: 2 | AP47: 1 | BE47: 91
A48: A301205.108 | B48: EMPUNHADURA UGA8HR3RD4RD | O48: 1 | Q48: 10 | S48: 4 | AB48: 18 | AC48: 12 | AE48: 2 | AG48: 16 | AL48: 1 | AM48: 1 | AO48: 6 | AP48: 2 | AQ48: 6 | AS48: 3 | BA48: 3 | BE48: 85
A49: ASP02300.023 | B49: CABO COAXIAL LMR-400 LOW LOSS 50OHM 1M TERMINAIS TNC MACHO | Q49: 80 | BE49: 80
A50: A102145.046 | B50: MÓDULO DECODIFICADOR PARA FIBRA OTICA LWLSD1 | O50: 2 | P50: 21 | Q50: 5 | X50: 4 | Y50: 1 | AA50: 8 | AC50: 10 | AD50: 2 | AF50: 4 | AG50: 2 | AH50: 7 | AQ50: 3 | AR50: 6 | AY50: 5 | BE50: 80
A51: G2EH-0003 | B51: ENCODER INCREMENTAL G2EH 1024PPR | J51: 7 | K51: 1 | M51: 10 | N51: 1 | O51: 3 | Q51: 3 | R51: 3 | S51: 15 | T51: 5 | V51: 1 | W51: 4 | Y51: 2 | AC51: 1 | AD51: 4 | AE51: 8 | AH51: 1 | AQ51: 1 | AV51: 3 | BB51: 6 | BE51: 79
A52: VNSK-00001 | B52: MANETE - FCD1131B1ESPESP+G18+ Y | F52: 2 | I52: 1 | L52: 3 | O52: 5 | P52: 4 | S52: 5 | V52: 1 | X52: 4 | AA52: 5 | AC52: 7 | AD52: 6 | AF52: 8 | AG52: 4 | AI52: 9 | AJ52: 6 | AK52: 6 | BB52: 2 | BE52: 78
A53: T65VAVMDP-0006 | B53: ENCODER ABSOLUTO CEV-65-M-DP 8192/4096 | D53: 1 | F53: 5 | H53: 2 | I53: 2 | J53: 6 | K53: 6 | L53: 1 | M53: 1 | P53: 5 | U53: 4 | V53: 1 | W53: 1 | X53: 5 | Y53: 2 | Z53: 2 | AB53: 1 | AF53: 4 | AG53: 1 | AH53: 4 | AI53: 1 | AK53: 2 | AL53: 2 | AO53: 1 | AR53: 1 | AT53: 6 | AU53: 1 | AY53: 1 | BE53: 69
A54: G2EH-0010 | B54: ENCODER INCREMENTAL G2EH 1024PPR COM BRACO DE TORQUE 500MM | G54: 1 | I54: 3 | J54: 13 | K54: 7 | O54: 4 | S54: 1 | U54: 7 | V54: 8 | W54: 5 | X54: 1 | Z54: 1 | AB54: 4 | AF54: 2 | AH54: 1 | AI54: 1 | AN54: 2 | AO54: 3 | AT54: 3 | AX54: 1 | BE54: 68
A55: A101409.005 | B55: BRACO DE TORQUE COMP. 500MM 6MM | C55: 5 | H55: 2 | J55: 8 | K55: 4 | L55: 1 | O55: 1 | S55: 4 | U55: 9 | X55: 4 | Y55: 1 | AB55: 3 | AE55: 1 | AF55: 1 | AG55: 2 | AI55: 1 | AJ55: 2 | AK55: 2 | AO55: 2 | AT55: 1 | AU55: 2 | AX55: 2 | AY55: 2 | AZ55: 5 | BB55: 1 | BE55: 66
A56: A111009.015 | B56: CONECTOR 4 POLOS M12 MACHO DCODED | I56: 4 | Q56: 30 | T56: 5 | AD56: 3 | AN56: 4 | AW56: 14 | BE56: 60
A57: VNSK-00086 | B57: MANETE - FDX1131A1050XXX+G18+Y | F57: 1 | H57: 2 | I57: 1 | L57: 2 | N57: 1 | O57: 5 | P57: 2 | Q57: 4 | R57: 6 | S57: 3 | U57: 6 | V57: 5 | W57: 3 | AA57: 5 | AB57: 5 | AE57: 9 | BE57: 60
A58: A102145.037 | B58: MÓDULO TRANSMISSOR DE FIBRA ÓTICA LWLST1 | O58: 2 | P58: 21 | W58: 2 | X58: 4 | Y58: 1 | AA58: 8 | AD58: 2 | AE58: 4 | AG58: 2 | AI58: 7 | AY58: 5 | BE58: 58
A59: ASP02159.004 | B59: ANTENA GNSS DE ALTO DESEMPENHO MC | D59: 2 | L59: 6 | N59: 14 | R59: 1 | V59: 1 | AC59: 8 | AI59: 2 | AM59: 9 | AV59: 2 | AX59: 8 | BB59: 5 | BE59: 58
A60: A302200.015 | B60: SENSOR PARA EMPUNHADURA ES080KNS0ES4142C | G60: 3 | N60: 3 | O60: 4 | Q60: 8 | X60: 12 | AJ60: 8 | AN60: 4 | AO60: 1 | AW60: 4 | AY60: 6 | BB60: 3 | BE60: 56
A61: A111001.002 | B61: CONECTOR 12 POLOS CONTACT FEMEA | C61: 6 | D61: 1 | E61: 2 | G61: 6 | H61: 6 | I61: 5 | M61: 4 | N61: 1 | P61: 1 | Q61: 1 | AB61: 5 | AE61: 1 | AG61: 6 | AH61: 2 | AJ61: 2 | AK61: 1 | AN61: 5 | AR61: 1 | BE61: 56
A62: A111205.007 | B62: CONECTOR 26 POLOS CONTACT FEMEA+ 20M CABO A100106.001+CONECTOR 24POLOS | H62: 8 | T62: 8 | AB62: 7 | AD62: 4 | AF62: 4 | AL62: 8 | BA62: 16 | BE62: 55
A63: A300200.001 | B63: BOTAO VERDE 1NA P9FGN | C63: 20 | G63: 1 | AI63: 8 | AJ63: 12 | AR63: 10 | BE63: 51
A64: A300200.002 | B64: BOTAO VERMELHO 1NA P9FRD | C64: 20 | AI64: 8 | AJ64: 12 | AR64: 10 | BE64: 50
A65: A100106.123 | B65: CABO FLEXIVEL 6 PARES TRANCADOS X 0,5MM² 300°C 750V PARA ENCODERS 100 COBRE | AW65: 50 | BE65: 50
A66: T65VAVMAN-0056 | B66: ENCODER CEV65 FUNCAO TACO 4-20MA 100RPM | C66: 2 | D66: 3 | J66: 1 | L66: 2 | R66: 7 | S66: 5 | V66: 2 | AA66: 1 | AB66: 1 | AD66: 2 | AG66: 2 | AH66: 10 | AM66: 2 | AT66: 6 | AX66: 3 | BE66: 49
A67: T65VAVMDP-0048 | B67: ENCODER ABSOLUTO CEV-65-M-DP 8192/4096 | F67: 3 | G67: 1 | H67: 2 | I67: 3 | L67: 5 | M67: 9 | P67: 4 | Q67: 6 | T67: 3 | V67: 5 | X67: 4 | BE67: 45
A68: A100106.050 | B68: 22M CABO FLEXIVEL 12X0,5MM² 300°C 300V PARA ENCODERS + CONECTOR M23 12 POL | E68: 7 | G68: 4 | H68: 6 | AE68: 8 | AN68: 2 | AQ68: 2 | AV68: 2 | AW68: 4 | AZ68: 10 | BE68: 45
A69: C830-00001 | B69: CONECTOR ROTATIVO MODULAR 830, 2X4A E 6X30A | H69: 4 | J69: 1 | P69: 6 | T69: 1 | V69: 2 | W69: 1 | Y69: 2 | Z69: 1 | AE69: 1 | AH69: 2 | AK69: 1 | AP69: 1 | AQ69: 5 | AS69: 3 | AT69: 1 | AU69: 3 | AY69: 1 | AZ69: 1 | BA69: 2 | BB69: 4 | BC69: 2 | BE69: 45
A70: VCS0-00376 | B70: MANETE - DM21B1030030+HOS COM PARAFUSOS PHILIPS | AK70: 2 | AO70: 6 | AV70: 8 | AY70: 4 | AZ70: 4 | BC70: 20 | BE70: 44
A71: T84VAVMDP-0001 | B71: ENCODER ABSOLUTO CEV-84-M-DP 4096/4096 | J71: 6 | K71: 1 | M71: 1 | O71: 2 | P71: 4 | R71: 10 | T71: 1 | Y71: 1 | AA71: 4 | AB71: 1 | AC71: 1 | AG71: 1 | AH71: 1 | AM71: 2 | AT71: 1 | AU71: 7 | BE71: 44
A72: A301205.377 | B72: KIT PLACA DE MONTAGEM TRANSPARENTE 96X96MM V048K3 C ESPELHO P CS0 NS0 IDV006F1 | E72: 1 | R72: 2 | S72: 8 | Y72: 2 | AA72: 2 | AB72: 5 | AC72: 4 | AK72: 4 | AM72: 2 | AS72: 2 | AU72: 7 | BB72: 3 | BE72: 42
A73: AG01130.691 | B73: TUBO RETANGULAR 100 X 50 X 3,00 X 6000MM ASTM A240 304 | H73: 42 | BE73: 42
A74: A301205.384 | B74: KIT PARA RETORNO POR MOLA VNS0 | H74: 2 | O74: 5 | Q74: 5 | U74: 1 | AA74: 2 | AB74: 7 | AE74: 5 | AL74: 4 | AM74: 6 | AO74: 3 | AU74: 2 | BE74: 42
A75: VNSK-00087 | B75: MANETE FDX1333F1050XXX G18 Y | F75: 2 | I75: 1 | J75: 1 | K75: 1 | W75: 3 | AB75: 6 | AE75: 6 | AH75: 6 | AJ75: 9 | AU75: 1 | AV75: 2 | AZ75: 2 | BE75: 40
A76: A301205.093 | B76: COIFA P/ EMPUNHADURA V041N UG | T76: 40 | BE76: 40
A77: T58VAVMPN-0019 | B77: ENCODER ABSOLUTO CEV58:2M PN 8192_4096 | H77: 2 | O77: 24 | Q77: 6 | AN77: 1 | AQ77: 6 | BE77: 39
A78: A100109.038 | B78: PAINEL DE CAMPO TRANSMISSOR COM CONJUNTO DE RECEPCAO DE SINAIS PARA 2 ENCODER | AX78: 39 | BE78: 39
A79: T48THAN-0033 | B79: TRANSDUTOR LINEAR LMR-48 ANALOGICO 1025MM C/ CURSOR | C79: 1 | K79: 14 | Q79: 14 | AX79: 2 | AY79: 2 | AZ79: 1 | BA79: 4 | BE79: 38
A80: T65VAVMAN-0001 | B80: ENCODER ABSOLUTO CEV-65-M-A 4096/4096 | C80: 1 | D80: 1 | H80: 3 | L80: 1 | O80: 2 | Q80: 1 | R80: 1 | U80: 2 | V80: 1 | Y80: 1 | AB80: 3 | AD80: 2 | AI80: 2 | AJ80: 1 | AK80: 2 | AN80: 1 | AO80: 9 | AQ80: 1 | AS80: 1 | AU80: 2 | BE80: 38
A81: T84VAVMDP-0011 | B81: ENCODER ABSOLUTO CEV-84-M-DP 4096/4096 + ACOPLAMENTO DUPLO 10/10 E PLAQUETA INOX | AP81: 38 | BE81: 38
A82: T58VABMDP-0004 | B82: ENCODER ABSOLUTO CES-58-M-DP 8192/4096 | F82: 2 | G82: 7 | I82: 1 | K82: 1 | P82: 1 | V82: 2 | Y82: 3 | Z82: 2 | AA82: 3 | AD82: 1 | AH82: 3 | AK82: 1 | AO82: 5 | AP82: 1 | AY82: 3 | BE82: 36
A83: AG01130.689 | B83: TUBO QUADRADO 50 X 50 X 3,00 X 6000MM ASTM A240 304 | H83: 36 | BE83: 36
A84: C435-00001 | B84: CONECTOR ROTATIVO MODULAR ROBUSTO 435, 4X30A (500VCA/CC) | E84: 1 | M84: 3 | O84: 2 | P84: 1 | R84: 6 | X84: 2 | Z84: 2 | AC84: 6 | AJ84: 2 | AT84: 3 | AV84: 3 | AZ84: 3 | BE84: 34
A85: VNS0-00235 | B85: MANETE-FDD1131B1050050 | F85: 2 | I85: 2 | P85: 1 | R85: 3 | S85: 1 | T85: 2 | X85: 1 | Z85: 1 | AB85: 2 | AD85: 1 | AF85: 1 | AK85: 2 | AL85: 2 | AM85: 2 | AS85: 3 | AT85: 3 | AW85: 1 | AY85: 3 | BE85: 33
A86: T58VAVMSS-0048 | B86: ENCODER ABSOLUTO CEV-58-M-SSI 8192/4096 | D86: 1 | G86: 4 | H86: 2 | J86: 2 | M86: 1 | O86: 1 | R86: 1 | S86: 1 | T86: 3 | U86: 1 | W86: 2 | X86: 2 | AB86: 1 | AE86: 1 | AJ86: 1 | AM86: 4 | AQ86: 1 | AT86: 1 | BA86: 3 | BE86: 33
A87: T58VABMET-0002 | B87: ENCODER ABSOLUTO CES-58-M-ET 8192/4096 | O87: 8 | P87: 3 | R87: 1 | U87: 2 | V87: 1 | AC87: 3 | AD87: 1 | AF87: 1 | AI87: 3 | AJ87: 1 | AM87: 4 | AN87: 2 | AP87: 2 | AR87: 1 | BE87: 33
A88: A301205.392 | B88: KIT BLOCO DE EIXO PARA HASTE NS128 | AW88: 6 | AY88: 12 | AZ88: 15 | BE88: 33
A89: A301206.013 | B89: APOIO DE BRACO AS130 | D89: 3 | E89: 2 | H89: 1 | R89: 5 | AE89: 2 | AH89: 1 | AS89: 4 | AT89: 4 | AU89: 2 | AX89: 1 | AY89: 6 | BB89: 1 | BE89: 32
A90: T84AVMPA-0007 | B90: ENCODER ABSOLUTO CE-84-M-P 4,44/4096 + CONECTOR 26 POLOS | G90: 13 | Z90: 1 | AB90: 7 | AE90: 4 | AM90: 1 | AY90: 1 | BA90: 4 | BE90: 31
A91: A110216.002 | B91: ACOPLAMENTO DE FOLE 10 10MM | C91: 1 | D91: 1 | E91: 2 | F91: 1 | I91: 2 | T91: 5 | W91: 2 | AD91: 5 | AF91: 2 | AJ91: 1 | AP91: 1 | AQ91: 2 | AY91: 5 | BC91: 1 | BE91: 31
A92: A110200.010 | B92: CPS 15_2 ACOPLAMENTO ELASTICO 10_14MM | J92: 4 | K92: 2 | S92: 1 | V92: 2 | Y92: 1 | AA92: 1 | AB92: 10 | AC92: 1 | AD92: 1 | AJ92: 1 | AL92: 5 | AM92: 1 | BE92: 30
A93: A101405.012 | B93: CURSOR PARA TRANSDUTOR LP46 | S93: 1 | AI93: 3 | AO93: 2 | AW93: 2 | BA93: 10 | BC93: 12 | BE93: 30
A94: A101411.102 | B94: RODA DE MEDICAO 300MM PARA ENCODER T 58 65 70 LADO DIREITO | E94: 1 | F94: 1 | G94: 2 | I94: 8 | L94: 1 | O94: 2 | AA94: 2 | AD94: 6 | AQ94: 1 | AV94: 2 | AY94: 3 | BE94: 29
A95: C330-00001 | B95: CONECTOR ROTATIVO MODULAR 330. 3X30A | C95: 1 | E95: 1 | F95: 1 | H95: 1 | O95: 1 | P95: 3 | S95: 2 | V95: 1 | W95: 1 | X95: 2 | Y95: 2 | AB95: 2 | AC95: 2 | AE95: 1 | AL95: 2 | AV95: 2 | AX95: 1 | AY95: 1 | BC95: 1 | BD95: 1 | BE95: 29
A96: T65VAVMPA-0006 | B96: ENCODER ABSOLUTO CEV-65-M-P 4096/4096 | F96: 1 | I96: 1 | J96: 7 | K96: 1 | U96: 1 | AB96: 2 | AJ96: 2 | AM96: 1 | AN96: 2 | AQ96: 1 | AS96: 8 | AY96: 1 | BE96: 28
A97: TLT100SSI-0004 | B97: TRANSDUTOR LT100-PI SSI- 100MM | W97: 2 | AG97: 4 | AJ97: 10 | AM97: 1 | AT97: 6 | AU97: 4 | BE97: 27
A98: A101405.002 | B98: ANEL MAGNETICO T4M33 PLASTICO | C98: 14 | H98: 4 | U98: 2 | AP98: 7 | BE98: 27
A99: T58VAVMSS-0001 | B99: ENCODER ABSOLUTO CEV-58-M-SSI 4096/4096 | E99: 1 | F99: 3 | J99: 1 | M99: 3 | Q99: 1 | U99: 1 | V99: 2 | W99: 3 | X99: 1 | Y99: 1 | AA99: 2 | AB99: 1 | AM99: 1 | AQ99: 4 | AR99: 1 | BC99: 1 | BE99: 27
A100: A101402.058 | B100: SISTEMA DE MEDICAO POR CABO 10M | L100: 1 | Q100: 2 | AB100: 2 | AD100: 8 | AK100: 2 | AN100: 2 | AS100: 1 | AU100: 2 | AV100: 1 | AZ100: 5 | BC100: 1 | BE100: 27
A101: A101127.009 | B101: MOLA DE FIXACAO PARA IEH58/CEH58 | G101: 2 | K101: 4 | M101: 4 | Q101: 10 | V101: 5 | AJ101: 2 | BE101: 27
...

Sheet Demanda Semestral
A1: DEMANDA SEMESTRAL (DIRETA + INDIRETA)
A2: Demanda total consolidada por semestre
A4: Código | B4: Descrição | C4: 2022-S1 | D4: 2022-S2 | E4: 2023-S1 | F4: 2023-S2 | G4: 2024-S1 | H4: 2024-S2 | I4: 2025-S1 | J4: 2025-S2 | K4: 2026-S1 | L4: Total
A5: A212001.013 | B5: TERMINAL CRIMPAVEL PARA CONECTOR MODULAR - 4A - RETO - BITOLA 0,25 - 0,75MM² | C5: 163 | D5: 590 | E5: 495 | F5: 1279 | G5: 872 | H5: 600 | I5: 316 | J5: 730 | K5: 560 | L5: 5605
A6: A100106.013 | B6: CABO EXTRA FLEXIVEL 6 PARES TRANCADOS 0,25MM2 PARA ENCODERS | C6: 1180 | D6: 1295 | E6: 50 | F6: 100 | I6: 1030 | L6: 3655
A7: A100106.012 | B7: CABO EXTRA FLEXIVEL 6 PARES TRANCADOS PARA ENCODERS | D7: 200 | F7: 100 | G7: 2 | H7: 12 | I7: 10 | J7: 2300 | L7: 2624
A8: AG00105.105 | B8: CABO UTP BLINDADO GIGALAN CAT.6 VERMELHO | E8: 865 | F8: 200 | G8: 50 | H8: 470 | I8: 40 | J8: 360 | L8: 1985
A9: C430-00001 | B9: CONECTOR ROTATIVO MODULAR 430, 2X4A E 2X30A | C9: 108 | D9: 147 | E9: 216 | F9: 235 | G9: 240 | H9: 223 | I9: 301 | J9: 319 | K9: 74 | L9: 1863
A10: A100106.105 | B10: CABO FLEXIVEL 4 PARES 0,5MM² PARA SINAL ANALOGICO | D10: 1050 | H10: 700 | L10: 1750
A11: A212001.012 | B11: TERMINAL CRIMPAVEL PARA CONECTOR MODULAR - 30A - RETO - BITOLA 1,5 - 2MM² | C11: 152 | D11: 20 | E11: 211 | F11: 350 | G11: 281 | H11: 112 | I11: 12 | J11: 24 | K11: 40 | L11: 1202
A12: ADS01423.003 | B12: TELA PARA WINDFENCE DUSTTAMER 6510 VERDE PERM 50 L 150CM (59 | F12: 1080 | L12: 1080
A13: A212001.015 | B13: TERMINAL CRIMPAVEL PARA CONECTOR MODULAR - 30A - 90º - BITOLA 1,5 - 2MM² | C13: 43 | D13: 50 | E13: 6 | F13: 200 | G13: 393 | H13: 59 | I13: 66 | J13: 4 | L13: 821
A14: C205-00001 | B14: CONECTOR ROTATIVO COAXIAL 205, 2X4A | C14: 60 | D14: 63 | E14: 54 | F14: 118 | G14: 140 | H14: 84 | I14: 112 | J14: 77 | K14: 76 | L14: 784
A15: A212001.011 | B15: ESPAQUETE TERMOENCOLHIVEL PARA ISOLACAO DE TERMINAIS CRIMPAVEIS | C15: 145 | D15: 400 | E15: 160 | I15: 3 | J15: 25 | K15: 50 | L15: 783
A16: STR04196.001 | B16: SERVICO DE ASSESSORIA DE VENDAS ID | C16: 78 | D16: 147 | E16: 98 | F16: 95 | G16: 35 | H16: 45 | I16: 75 | J16: 22 | K16: 13 | L16: 608
A17: C430-00002 | B17: CONECTOR ROTATIVO MODULAR 430-SS, 4X30A | C17: 21 | D17: 32 | E17: 46 | F17: 39 | G17: 49 | H17: 53 | I17: 92 | J17: 52 | K17: 155 | L17: 539
A18: AG01137.002 | B18: SONDA DE AMOSTRAGEM TLC-40-150-ZR1 | H18: 224 | K18: 280 | L18: 504
A19: ADS01127.003 | B19: CORDOALHA PARA AMARRAÇÃO DA TELA PARA WINDFENCE | F19: 450 | L19: 450
A20: A212001.005 | B20: SOQUETE DE 2 POLOS PARA CONECTOR COAXIAL 205 COM 2 TERMINAIS SOLDAVEIS | C20: 34 | D20: 43 | E20: 28 | F20: 50 | G20: 73 | H20: 51 | I20: 53 | J20: 53 | K20: 40 | L20: 425
A21: A100106.113 | B21: CABO PROFINET TIPO B 2 PARES 22 AWG | J21: 420 | L21: 420
A22: A212003.003 | B22: KIT PLUGS COMPLETO MONTADO PARA CONECTOR 430 C/ 4 RABICHOS DE 30 CM | C22: 13 | D22: 20 | E22: 30 | F22: 66 | G22: 68 | H22: 24 | I22: 51 | J22: 62 | K22: 55 | L22: 389
A23: AG00107.059 | B23: PASSA CABO EM BORRACHA P/ VNSK | C23: 29 | D23: 33 | E23: 43 | F23: 43 | G23: 89 | H23: 56 | I23: 19 | J23: 38 | K23: 30 | L23: 380
A24: AG01122.009 | B24: SONDA DE AMOSTRAGEM POR IMERSÃO TLC-25-120-ZR1 | H24: 20 | J24: 35 | K24: 280 | L24: 335
A25: AG01122.007 | B25: SONDA DE AMOSTRAGEM POR IMERSÃO TB-25-120-ZR1 | H25: 20 | J25: 10 | K25: 280 | L25: 310
A26: A100106.053 | B26: CABO BLINDADO 3 PARES TRANÇADOS 0,5MM² PARA ENCODERS | H26: 3 | I26: 290 | J26: 10 | L26: 303
A27: A301205.067 | B27: COIFA PARA ESPELHO DE 96X96MM V041N | C27: 15 | D27: 23 | E27: 60 | F27: 11 | G27: 43 | H27: 19 | I27: 26 | J27: 40 | K27: 18 | L27: 255
A28: A212001.007 | B28: RECEPTACULO DE 2 POLOS PARA CONECTOR COAXIAL 205 COM 2 RABICHOS DE 15CM | C28: 21 | D28: 21 | E28: 28 | F28: 22 | G28: 23 | H28: 29 | I28: 25 | J28: 31 | K28: 41 | L28: 241
A29: A100106.001 | B29: CABO COM MALHA TRANCADA 26X0,14MM2 | F29: 115 | H29: 100 | L29: 215
A30: A212001.006 | B30: RECEPTÁCULO DE 2 POLOS PARA CONECTOR COAXIAL 205 COM TERMINAL SOLDÁVEL | C30: 23 | D30: 5 | E30: 3 | F30: 56 | G30: 49 | H30: 14 | I30: 26 | J30: 22 | K30: 8 | L30: 206
A31: A300200.017 | B31: MODULO DE CONTATO P/ NS0 | C31: 10 | E31: 34 | F31: 33 | G31: 4 | H31: 57 | I31: 10 | J31: 32 | K31: 16 | L31: 196
A32: A301205.434 | B32: COIFA PARA MANETE VNS0 NNS0 VCS0 HS2 27 | C32: 15 | D32: 4 | E32: 49 | G32: 7 | H32: 15 | I32: 46 | J32: 27 | K32: 32 | L32: 195
A33: A100106.004 | B33: CABO BLINDADO FLEXIVEL PARA ENCODER SSI | E33: 100 | I33: 80 | L33: 180
A34: A300200.054 | B34: BOTAO 1NA P9F | C34: 14 | E34: 57 | F34: 38 | H34: 26 | I34: 17 | J34: 9.1 | K34: 14 | L34: 175.1
A35: A101409.086 | B35: BRACO DE TORQUE COMP. 100MM 6MM | H35: 160 | L35: 160
A36: A100106.023 | B36: CABO BLINDADO FLEXIVEL 4X0,25MM PAR TRANCADO | G36: 150 | L36: 150
A37: C630-00001 | B37: CONECTOR ROTATIVO MODULAR 630, 2X4A E 4X30A | C37: 11 | D37: 5 | E37: 21 | F37: 12 | G37: 22 | H37: 16 | I37: 10 | J37: 25 | K37: 15 | L37: 137
A38: A111009.007 | B38: CONECTOR 4 POLOS M12 FEMEA ACODED | C38: 5 | D38: 18 | E38: 72 | F38: 8 | G38: 27 | H38: 2 | I38: 3 | L38: 135
A39: AOR00106.127 | B39: MULTICABO 12 VIAS (1 COAXIAL, 12 DADOS) | I39: 125 | L39: 125
A40: C230-00001 | B40: CONECTOR ROTATIVO MODULAR 230, 2X30A | C40: 14 | D40: 7 | E40: 6 | F40: 13 | G40: 18 | H40: 16 | I40: 14 | J40: 11 | K40: 19 | L40: 118
A41: AG00102.388 | B41: REGUA DE BORNES PARA SISTEMA FRISOLUB SEM DISJUNTOR | D41: 108 | G41: 1 | L41: 109
A42: C230-00002 | B42: CONECTOR ROTATIVO MODULAR 230-SS, 2X30A | C42: 10 | D42: 4 | E42: 8 | F42: 9 | G42: 14 | H42: 9 | I42: 17 | J42: 25 | K42: 4 | L42: 100
A43: A212001.017 | B43: TERMINAL CRIMPAVEL PARA CONECTOR MODULAR - 30A - RETO- C/ PROTECAO - BITOLA 3-6MM2 | C43: 25 | E43: 10 | I43: 3 | J43: 20 | K43: 40 | L43: 98
A44: T65VAVMDP-0001 | B44: ENCODER ABSOLUTO CEV-65-M-DP 4096/4096 | C44: 12 | D44: 11 | E44: 10 | F44: 3 | G44: 15 | H44: 16 | I44: 14 | J44: 10 | K44: 4 | L44: 95
A45: A212001.014 | B45: TERMINAL CRIMPAVEL PARA CONECTOR MODULAR - 30A - RETO - BITOLA 1,5 - 2MM2 | C45: 25 | D45: 10 | J45: 20 | K45: 40 | L45: 95
A46: A301205.435 | B46: COIFA PARA MANETE VNS0 E VCS0 HS2 27 UGA | E46: 13 | F46: 23 | G46: 10 | H46: 23 | I46: 15 | J46: 2.1 | K46: 5 | L46: 91.1
A47: A111009.006 | B47: CONECTOR 4 POLOS M12 MACHO DCODED | C47: 4 | D47: 15 | E47: 37 | F47: 8 | G47: 24 | H47: 2 | I47: 1 | L47: 91
A48: A301205.108 | B48: EMPUNHADURA UGA8HR3RD4RD | E48: 15 | G48: 32 | H48: 17 | I48: 15 | J48: 3 | K48: 3 | L48: 85
A49: ASP02300.023 | B49: CABO COAXIAL LMR-400 LOW LOSS 50OHM 1M TERMINAIS TNC MACHO | E49: 80 | L49: 80
A50: A102145.046 | B50: MÓDULO DECODIFICADOR PARA FIBRA OTICA LWLSD1 | E50: 28 | F50: 5 | G50: 24 | H50: 9 | I50: 9 | K50: 5 | L50: 80
A51: G2EH-0003 | B51: ENCODER INCREMENTAL G2EH 1024PPR | D51: 19 | E51: 29 | F51: 7 | G51: 13 | H51: 1 | I51: 1 | J51: 3 | K51: 6 | L51: 79
A52: VNSK-00001 | B52: MANETE - FCD1131B1ESPESP+G18+ Y | C52: 2 | D52: 4 | E52: 14 | F52: 5 | G52: 26 | H52: 25 | K52: 2 | L52: 78
A53: T65VAVMDP-0006 | B53: ENCODER ABSOLUTO CEV-65-M-DP 8192/4096 | C53: 8 | D53: 16 | E53: 5 | F53: 15 | G53: 5 | H53: 10 | I53: 2 | J53: 7 | K53: 1 | L53: 69
A54: G2EH-0010 | B54: ENCODER INCREMENTAL G2EH 1024PPR COM BRACO DE TORQUE 500MM | C54: 1 | D54: 23 | E54: 5 | F54: 22 | G54: 6 | H54: 2 | I54: 5 | J54: 4 | L54: 68
A55: A101409.005 | B55: BRACO DE TORQUE COMP. 500MM 6MM | C55: 7 | D55: 13 | E55: 5 | F55: 14 | G55: 5 | H55: 7 | I55: 2 | J55: 5 | K55: 8 | L55: 66
A56: A111009.015 | B56: CONECTOR 4 POLOS M12 MACHO DCODED | D56: 4 | E56: 35 | G56: 3 | I56: 4 | J56: 14 | L56: 60
A57: VNSK-00086 | B57: MANETE - FDX1131A1050XXX+G18+Y | C57: 3 | D57: 4 | E57: 20 | F57: 14 | G57: 19 | L57: 60
A58: A102145.037 | B58: MÓDULO TRANSMISSOR DE FIBRA ÓTICA LWLST1 | E58: 23 | F58: 7 | G58: 14 | H58: 9 | K58: 5 | L58: 58
A59: ASP02159.004 | B59: ANTENA GNSS DE ALTO DESEMPENHO MC | C59: 2 | D59: 20 | E59: 1 | F59: 1 | G59: 8 | H59: 2 | I59: 9 | J59: 10 | K59: 5 | L59: 58
A60: A302200.015 | B60: SENSOR PARA EMPUNHADURA ES080KNS0ES4142C | C60: 3 | D60: 3 | E60: 12 | F60: 12 | H60: 8 | I60: 5 | J60: 4 | K60: 9 | L60: 56
A61: A111001.002 | B61: CONECTOR 12 POLOS CONTACT FEMEA | C61: 21 | D61: 10 | E61: 2 | G61: 6 | H61: 11 | I61: 6 | L61: 56
A62: A111205.007 | B62: CONECTOR 26 POLOS CONTACT FEMEA+ 20M CABO A100106.001+CONECTOR 24POLOS | C62: 8 | E62: 8 | G62: 15 | H62: 8 | K62: 16 | L62: 55
A63: A300200.001 | B63: BOTAO VERDE 1NA P9FGN | C63: 21 | H63: 20 | I63: 10 | L63: 51
A64: A300200.002 | B64: BOTAO VERMELHO 1NA P9FRD | C64: 20 | H64: 20 | I64: 10 | L64: 50
A65: A100106.123 | B65: CABO FLEXIVEL 6 PARES TRANCADOS X 0,5MM² 300°C 750V PARA ENCODERS 100 COBRE | J65: 50 | L65: 50
A66: T65VAVMAN-0056 | B66: ENCODER CEV65 FUNCAO TACO 4-20MA 100RPM | C66: 5 | D66: 3 | E66: 12 | F66: 2 | G66: 4 | H66: 12 | I66: 2 | J66: 9 | L66: 49
A67: T65VAVMDP-0048 | B67: ENCODER ABSOLUTO CEV-65-M-DP 8192/4096 | C67: 6 | D67: 17 | E67: 13 | F67: 9 | L67: 45
A68: A100106.050 | B68: 22M CABO FLEXIVEL 12X0,5MM² 300°C 300V PARA ENCODERS + CONECTOR M23 12 POL | C68: 17 | G68: 8 | I68: 4 | J68: 6 | K68: 10 | L68: 45
A69: C830-00001 | B69: CONECTOR ROTATIVO MODULAR 830, 2X4A E 6X30A | C69: 4 | D69: 1 | E69: 7 | F69: 6 | G69: 1 | H69: 3 | I69: 6 | J69: 7 | K69: 10 | L69: 45
A70: VCS0-00376 | B70: MANETE - DM21B1030030+HOS COM PARAFUSOS PHILIPS | H70: 2 | I70: 6 | J70: 8 | K70: 28 | L70: 44
A71: T84VAVMDP-0001 | B71: ENCODER ABSOLUTO CEV-84-M-DP 4096/4096 | D71: 8 | E71: 17 | F71: 1 | G71: 6 | H71: 2 | I71: 2 | J71: 8 | L71: 44
A72: A301205.377 | B72: KIT PLACA DE MONTAGEM TRANSPARENTE 96X96MM V048K3 C ESPELHO P CS0 NS0 IDV006F1 | C72: 1 | E72: 10 | F72: 2 | G72: 11 | H72: 4 | I72: 2 | J72: 9 | K72: 3 | L72: 42
A73: AG01130.691 | B73: TUBO RETANGULAR 100 X 50 X 3,00 X 6000MM ASTM A240 304 | C73: 42 | L73: 42
A74: A301205.384 | B74: KIT PARA RETORNO POR MOLA VNS0 | C74: 2 | E74: 10 | F74: 1 | G74: 14 | H74: 4 | I74: 9 | J74: 2 | L74: 42
A75: VNSK-00087 | B75: MANETE FDX1333F1050XXX G18 Y | C75: 2 | D75: 3 | F75: 3 | G75: 12 | H75: 15 | J75: 3 | K75: 2 | L75: 40
A76: A301205.093 | B76: COIFA P/ EMPUNHADURA V041N UG | E76: 40 | L76: 40
A77: T58VAVMPN-0019 | B77: ENCODER ABSOLUTO CEV58:2M PN 8192_4096 | C77: 2 | E77: 30 | I77: 7 | L77: 39
A78: A100109.038 | B78: PAINEL DE CAMPO TRANSMISSOR COM CONJUNTO DE RECEPCAO DE SINAIS PARA 2 ENCODER | J78: 39 | L78: 39
A79: T48THAN-0033 | B79: TRANSDUTOR LINEAR LMR-48 ANALOGICO 1025MM C/ CURSOR | C79: 1 | D79: 14 | E79: 14 | J79: 2 | K79: 7 | L79: 38
A80: T65VAVMAN-0001 | B80: ENCODER ABSOLUTO CEV-65-M-A 4096/4096 | C80: 5 | D80: 1 | E80: 4 | F80: 4 | G80: 5 | H80: 5 | I80: 11 | J80: 3 | L80: 38
A81: T84VAVMDP-0011 | B81: ENCODER ABSOLUTO CEV-84-M-DP 4096/4096 + ACOPLAMENTO DUPLO 10/10 E PLAQUETA INOX | I81: 38 | L81: 38
A82: T58VABMDP-0004 | B82: ENCODER ABSOLUTO CES-58-M-DP 8192/4096 | C82: 9 | D82: 2 | E82: 1 | F82: 7 | G82: 4 | H82: 4 | I82: 6 | K82: 3 | L82: 36
A83: AG01130.689 | B83: TUBO QUADRADO 50 X 50 X 3,00 X 6000MM ASTM A240 304 | C83: 36 | L83: 36
A84: C435-00001 | B84: CONECTOR ROTATIVO MODULAR ROBUSTO 435, 4X30A (500VCA/CC) | C84: 1 | D84: 3 | E84: 9 | F84: 4 | G84: 6 | H84: 2 | J84: 6 | K84: 3 | L84: 34
A85: VNS0-00235 | B85: MANETE-FDD1131B1050050 | C85: 2 | D85: 2 | E85: 7 | F85: 2 | G85: 4 | H85: 4 | I85: 2 | J85: 7 | K85: 3 | L85: 33
A86: T58VAVMSS-0048 | B86: ENCODER ABSOLUTO CEV-58-M-SSI 8192/4096 | C86: 7 | D86: 3 | E86: 6 | F86: 5 | G86: 2 | H86: 1 | I86: 5 | J86: 1 | K86: 3 | L86: 33
A87: T58VABMET-0002 | B87: ENCODER ABSOLUTO CES-58-M-ET 8192/4096 | E87: 12 | F87: 3 | G87: 5 | H87: 4 | I87: 9 | L87: 33
A88: A301205.392 | B88: KIT BLOCO DE EIXO PARA HASTE NS128 | J88: 6 | K88: 27 | L88: 33
A89: A301206.013 | B89: APOIO DE BRACO AS130 | C89: 6 | E89: 5 | G89: 2 | H89: 1 | J89: 11 | K89: 7 | L89: 32
A90: T84AVMPA-0007 | B90: ENCODER ABSOLUTO CE-84-M-P 4,44/4096 + CONECTOR 26 POLOS | C90: 13 | F90: 1 | G90: 11 | I90: 1 | K90: 5 | L90: 31
A91: A110216.002 | B91: ACOPLAMENTO DE FOLE 10 10MM | C91: 5 | D91: 2 | E91: 5 | F91: 2 | G91: 7 | H91: 1 | I91: 3 | K91: 6 | L91: 31
A92: A110200.010 | B92: CPS 15_2 ACOPLAMENTO ELASTICO 10_14MM | D92: 6 | E92: 1 | F92: 3 | G92: 13 | H92: 6 | I92: 1 | L92: 30
A93: A101405.012 | B93: CURSOR PARA TRANSDUTOR LP46 | E93: 1 | H93: 3 | I93: 2 | J93: 2 | K93: 22 | L93: 30
A94: A101411.102 | B94: RODA DE MEDICAO 300MM PARA ENCODER T 58 65 70 LADO DIREITO | C94: 4 | D94: 9 | E94: 2 | G94: 8 | I94: 1 | J94: 2 | K94: 3 | L94: 29
A95: C330-00001 | B95: CONECTOR ROTATIVO MODULAR 330. 3X30A | C95: 4 | E95: 6 | F95: 6 | G95: 5 | H95: 2 | J95: 3 | K95: 3 | L95: 29
A96: T65VAVMPA-0006 | B96: ENCODER ABSOLUTO CEV-65-M-P 4096/4096 | C96: 1 | D96: 9 | F96: 1 | G96: 2 | H96: 2 | I96: 4 | J96: 8 | K96: 1 | L96: 28
A97: TLT100SSI-0004 | B97: TRANSDUTOR LT100-PI SSI- 100MM | F97: 2 | H97: 14 | I97: 1 | J97: 10 | L97: 27
A98: A101405.002 | B98: ANEL MAGNETICO T4M33 PLASTICO | C98: 18 | F98: 2 | I98: 7 | L98: 27
A99: T58VAVMSS-0001 | B99: ENCODER ABSOLUTO CEV-58-M-SSI 4096/4096 | C99: 4 | D99: 4 | E99: 1 | F99: 8 | G99: 3 | I99: 6 | K99: 1 | L99: 27
A100: A101402.058 | B100: SISTEMA DE MEDICAO POR CABO 10M | D100: 1 | E100: 2 | G100: 10 | H100: 2 | I100: 2 | J100: 4 | K100: 6 | L100: 27
A101: A101127.009 | B101: MOLA DE FIXACAO PARA IEH58/CEH58 | C101: 2 | D101: 8 | E101: 10 | F101: 5 | H101: 2 | L101: 27
...

Sheet Ranking Top 50
A1: RANKING — TOP 50 ITENS POR DEMANDA TOTAL
A4: Rank | B4: Código | C4: Descrição | D4: Demanda Total (un) | E4: Demanda Direta | F4: Demanda Indireta
A5: 1 | B5: A212001.013 | C5: TERMINAL CRIMPAVEL PARA CONECTOR MODULAR - 4A - RETO - BITOLA 0,25 - 0,75MM² | D5: 5605 | E5: 5605 | F5: 0
A6: 2 | B6: A100106.013 | C6: CABO EXTRA FLEXIVEL 6 PARES TRANCADOS 0,25MM2 PARA ENCODERS | D6: 3655 | E6: 3655 | F6: 0
A7: 3 | B7: A100106.012 | C7: CABO EXTRA FLEXIVEL 6 PARES TRANCADOS PARA ENCODERS | D7: 2624 | E7: 2624 | F7: 0
A8: 4 | B8: AG00105.105 | C8: CABO UTP BLINDADO GIGALAN CAT.6 VERMELHO | D8: 1985 | E8: 1985 | F8: 0
A9: 5 | B9: C430-00001 | C9: CONECTOR ROTATIVO MODULAR 430, 2X4A E 2X30A | D9: 1863 | E9: 1863 | F9: 0
A10: 6 | B10: A100106.105 | C10: CABO FLEXIVEL 4 PARES 0,5MM² PARA SINAL ANALOGICO | D10: 1750 | E10: 1750 | F10: 0
A11: 7 | B11: A212001.012 | C11: TERMINAL CRIMPAVEL PARA CONECTOR MODULAR - 30A - RETO - BITOLA 1,5 - 2MM² | D11: 1202 | E11: 1202 | F11: 0
A12: 8 | B12: ADS01423.003 | C12: TELA PARA WINDFENCE DUSTTAMER 6510 VERDE PERM 50 L 150CM (59 | D12: 1080 | E12: 1080 | F12: 0
A13: 9 | B13: A212001.015 | C13: TERMINAL CRIMPAVEL PARA CONECTOR MODULAR - 30A - 90º - BITOLA 1,5 - 2MM² | D13: 821 | E13: 821 | F13: 0
A14: 10 | B14: C205-00001 | C14: CONECTOR ROTATIVO COAXIAL 205, 2X4A | D14: 784 | E14: 784 | F14: 0
A15: 11 | B15: A212001.011 | C15: ESPAQUETE TERMOENCOLHIVEL PARA ISOLACAO DE TERMINAIS CRIMPAVEIS | D15: 783 | E15: 783 | F15: 0
A16: 12 | B16: STR04196.001 | C16: SERVICO DE ASSESSORIA DE VENDAS ID | D16: 608 | E16: 608 | F16: 0
... A54: 50 | B54: G2EH-0010 | C54: ENCODER INCREMENTAL G2EH 1024PPR COM BRACO DE TORQUE 500MM | D54: 68 | E54: 68 | F54: 0

Sheet Uso em Estruturas (BOM)
A1: USO EM ESTRUTURAS (BILL OF MATERIALS)
A2: Estruturas em que o item aparece como componente e a demanda indireta gerada
A4: Componente | B4: Descrição Componente | C4: Estrutura (Pai) | D4: Qtd por Unidade | E4: Vendas do Pai (un, janela) | F4: Demanda Indireta Gerada (un)
A5: AG00107.059 | B5: PASSA CABO EM BORRACHA P/ VNSK | C5: 2-DM-12139 | D5: 1 | E5: 0 | F5: 0
A6: AG00107.059 | B6: PASSA CABO EM BORRACHA P/ VNSK | C6: S304182.069 | D6: 1 | E6: 1 | F6: 1
A7: AG00107.059 | B7: PASSA CABO EM BORRACHA P/ VNSK | C7: S304182.070 | D7: 1 | E7: 1 | F7: 1
A8: AG00107.059 | B8: PASSA CABO EM BORRACHA P/ VNSK | C8: VCSK-00005 | D8: 1 | E8: 0 | F8: 0
A9: AG00107.059 | B9: PASSA CABO EM BORRACHA P/ VNSK | C9: VCSK-00007 | D9: 1 | E9: 0 | F9: 0
A10: AG00107.059 | B10: PASSA CABO EM BORRACHA P/ VNSK | C10: VNS0-00055 | D10: 1 | E10: 8 | F10: 8
A11: AG00107.059 | B11: PASSA CABO EM BORRACHA P/ VNSK | C11: VNS0-00070 | D11: 1 | E11: 2 | F11: 2
A12: AG00107.059 | B12: PASSA CABO EM BORRACHA P/ VNSK | C12: VNS0-00279 | D12: 1 | E12: 0 | F12: 0
A13: AG00107.059 | B13: PASSA CABO EM BORRACHA P/ VNSK | C13: VNS0-00448 | D13: 1 | E13: 4 | F13: 4
A14: AG00107.059 | B14: PASSA CABO EM BORRACHA P/ VNSK | C14: VNS0-00661 | D14: 1 | E14: 0 | F14: 0
A15: AG00107.059 | B15: PASSA CABO EM BORRACHA P/ VNSK | C15: VNS0-00665 | D15: 1 | E15: 0 | F15: 0
A16: AG00107.059 | B16: PASSA CABO EM BORRACHA P/ VNSK | C16: VNS0-00923 | D16: 1 | E16: 0 | F16: 0
... A159: AG00107.059 | B159: PASSA CABO EM BORRACHA P/ VNSK | C159: VNSK-VLC2 | D159: 1 | E159: 6 | F159: 6

Sheet Base Vendas
A1: Produto | B1: Descrição | C1: Mês | D1: Quantidade
A2: 2-DM-12974 | B2: CONJ DA EMPUNHADURA G18 SENSOR KG0009 12MM | C2: 2026-01 | D2: 1
A3: A100106.001 | B3: CABO COM MALHA TRANCADA 26x0,1 | C3: 2023-07 | D3: 100
A4: A100106.001 | B4: CABO COM MALHA TRANCADA 26x0,1 | C4: 2023-11 | D4: 15
A5: A100106.001 | B5: CABO COM MALHA TRANCADA 26x0,1 | C5: 2024-09 | D5: 100
A6: A100106.004 | B6: CABO BLINDADO FLEXIVEL PARA ENCODER SSI | C6: 2023-05 | D6: 100
A7: A100106.004 | B7: CABO BLINDADO FLEXIVEL PARA ENCODER SSI | C7: 2025-05 | D7: 80
A8: A100106.012 | B8: CABO EXTRA FLEXIVEL 6 PARES TRANCADOS PARA ENCODERS | C8: 2022-11 | D8: 200
A9: A100106.012 | B9: CABO EXTRA FLEXIVEL 6 PARES TRANCADOS PARA ENCODERS | C9: 2023-11 | D9: 100
A10: A100106.012 | B10: CABO EXTRA FLEXIVEL 6 PARES TRANCADOS PARA ENCODERS | C10: 2024-05 | D10: 2
A11: A100106.012 | B11: CABO EXTRA FLEXIVEL 6 PARES TRANCADOS PARA ENCODERS | C11: 2024-07 | D11: 2
A12: A100106.012 | B12: CABO EXTRA FLEXIVEL 6 PARES TRANCADOS PARA ENCODERS | C12: 2024-12 | D12: 10
A13: A100106.012 | B13: CABO EXTRA FLEXIVEL 6 PARES TRANCADOS PARA ENCODERS | C13: 2025-06 | D13: 10
... A3974: WDSISPM-0011 | B3974: SOLUÇÃO MICRO-ONDAS DETECÇÃO D | C3974: 2023-08 | D3974: 3

Sheet Base Cadastro
A1: Código | B1: Descrição | C1: Tipo | D1: Un | E1: Lead Time (dias)
A2: *BRSPIN-0110* | B2: CELULA DE CARGA TIPO PINO 0201 10T -0,05...0,05 MV/V DAKRON | C2: PA | D2: PC | E2: 60
A3: 1-DM-08303-03 | B3: EIXO USINADO PARA ENCODER DE EIXO VAZADO | C3: PA | D3: PC | E3: 75
A4: 1-DM-12531 | B4: SUPORTE PARA ENCODERS G40 PADRAO ZB 85 COM ACOP ROTEX | C4: PA | D4: PC | E4: 75
A5: 1-DM-13520 | B5: EIXO BRACO P/ TORQUE PARA ENCODER HUBNER | C5: MP | D5: PC | E5: 75
A6: 1-DM-13556 | B6: FLANGE DISTANCIADORA DO ENCODER G40 | C6: MP | D6: PC | E6: 75
A7: 1-DM-13557 | B7: BUCHA DISTANCIADORA DO BRACO DE TORQUE | C7: MP | D7: PC | E7: 75
A8: 1-DM-13561 | B8: ENGRENAGEM DE ACIONAMENTO DOS CONTATOS P/ VNS0D | C8: MP | D8: PC | E8: 75
A9: 1-DM-13562 | B9: SUPORTE DE SUSTENTACAO PARA CAPA DE PROTECAO PARA CAMERAS ORLACO FAMOS 118º | C9: MP | D9: PC | E9: 75
A10: 1-DM-13563 | B10: RODA DE FERRO FUNDIDO E BANDA DE BORRACHA D125MM | C10: MP | D10: PC | E10: 75
A11: 2-DM-03169 | B11: ANEL DE SUPORTE DA BASE DO POSTO | C11: PA | D11: PC | E11: 75
A12: 2-DM-03170 | B12: FLANGE DE FIXACAO DO POSTO | C12: PA | D12: PC | E12: 75
A13: 2-DM-08043 | B13: GUIA MOVEL DAS ESFERAS FUNDIDA | C13: MP | D13: PC | E13: 75
... A23378: ZZZLOCALIZADO | B23378: MAGNETO DE CURSOR PARA TRANSDUTOR LP38 | C23378: PA | D23378: PC | E23378: 75

Sheet Base BOM
A1: Estrutura (Pai) | B1: Componente | C1: Descrição | D1: Qtd
A2: 2-DM-12139 | B2: AG00107.059 | C2: PASSA CABO EM BORRACHA P/ VNSK | D2: 1
A3: S304182.069 | B3: AG00107.059 | C3: PASSA CABO EM BORRACHA P/ VNSK | D3: 1
A4: S304182.070 | B4: AG00107.059 | C4: PASSA CABO EM BORRACHA P/ VNSK | D4: 1
A5: VCSK-00005 | B5: AG00107.059 | C5: PASSA CABO EM BORRACHA P/ VNSK | D5: 1
A6: VCSK-00007 | B6: AG00107.059 | C6: PASSA CABO EM BORRACHA P/ VNSK | D6: 1
A7: VNS0-00055 | B7: AG00107.059 | C7: PASSA CABO EM BORRACHA P/ VNSK | D7: 1
A8: VNS0-00070 | B8: AG00107.059 | C8: PASSA CABO EM BORRACHA P/ VNSK | D8: 1
A9: VNS0-00279 | B9: AG00107.059 | C9: PASSA CABO EM BORRACHA P/ VNSK | D9: 1
A10: VNS0-00448 | B10: AG00107.059 | C10: PASSA CABO EM BORRACHA P/ VNSK | D10: 1
A11: VNS0-00661 | B11: AG00107.059 | C11: PASSA CABO EM BORRACHA P/ VNSK | D11: 1
A12: VNS0-00665 | B12: AG00107.059 | C12: PASSA CABO EM BORRACHA P/ VNSK | D12: 1
A13: VNS0-00923 | B13: AG00107.059 | C13: PASSA CABO EM BORRACHA P/ VNSK | D13: 1
... A156: VNSK-VLC2 | B156: AG00107.059 | C156: PASSA CABO EM BORRACHA P/ VNSK | D156: 1
